instanceSlackBot/__init__.py
instanceSlackBot/instanceSlackBot.py
instanceSlackBot-1.2.6.dist-info/LICENSE
instanceSlackBot-1.2.6.dist-info/METADATA
instanceSlackBot-1.2.6.dist-info/WHEEL
instanceSlackBot-1.2.6.dist-info/top_level.txt
instanceSlackBot-1.2.6.dist-info/RECORD
