Metadata-Version: 2.1
Name: instanceSlackBot
Version: 1.2.6
Summary: UNKNOWN
Home-page: https://github.com/Dai-H15/InstanceSlackBot
Author: Daichi Matsumoto
Author-email: s1f102200828@iniad.org
License: MIT
Download-URL: https://github.com/Dai-H15/InstanceSlackBot
Platform: UNKNOWN
Requires-Python: >=3.6
License-File: LICENSE
Requires-Dist: slack-sdk (>=3.31.0)
